lostinmsh/__init__.py
lostinmsh/border.py
lostinmsh/circular_iterable.py
lostinmsh/closest_points.py
lostinmsh/geometry.py
lostinmsh/gmsh_context_manager.py
lostinmsh/mesh.py
lostinmsh/mesh_border.py
lostinmsh/mesh_lost.py
lostinmsh/plot.py
lostinmsh/polygon.py
lostinmsh/py.typed
lostinmsh/smallest_boundary.py
lostinmsh-0.0.2.dist-info/LICENSE
lostinmsh-0.0.2.dist-info/WHEEL
lostinmsh-0.0.2.dist-info/METADATA
lostinmsh-0.0.2.dist-info/RECORD
