Metadata-Version: 2.1
Name: lostinmsh
Version: 0.0.2
Summary: GMSH toolbox for locally structured meshes on polygon.
Author-email: Zoïs Moitier <zois.moitier@ensta-paris.fr>, Camille Carvalho <camille.carvalho@insa-lyon.fr>
Requires-Python: >=3.10
Classifier: Intended Audience :: Science/Research
Classifier: License :: OSI Approved :: MIT License
Classifier: Programming Language :: Python :: 3 :: Only
Classifier: Topic :: Scientific/Engineering :: Mathematics
Classifier: Topic :: Software Development :: Libraries :: Python Modules
Requires-Dist: gmsh
Requires-Dist: numpy
Requires-Dist: matplotlib ; extra == "all"
Requires-Dist: black ; extra == "dev"
Requires-Dist: flit ; extra == "dev"
Requires-Dist: isort ; extra == "dev"
Requires-Dist: mypy ; extra == "dev"
Requires-Dist: pylint ; extra == "dev"
Requires-Dist: pytest ; extra == "dev"
Requires-Dist: pytest-cov ; extra == "dev"
Requires-Dist: Sphinx ; extra == "doc"
Requires-Dist: sphinx-copybutton ; extra == "doc"
Requires-Dist: sphinx_rtd_theme ; extra == "doc"
Project-URL: Documentation, https://zmoitier.github.io/lostinmsh/
Project-URL: Source, https://github.com/zmoitier/lostinmsh
Provides-Extra: all
Provides-Extra: dev
Provides-Extra: doc
